lucide_flask/__init__.py
lucide_flask-1.0.dist-info/licenses/LICENSE
lucide_flask-1.0.dist-info/METADATA
lucide_flask-1.0.dist-info/WHEEL
lucide_flask-1.0.dist-info/top_level.txt
lucide_flask-1.0.dist-info/RECORD
