Metadata-Version: 2.4
Name: lucide-flask
Version: 1.0
Summary: A lucide icon extension for Flask.
Author: Praveen CJ
License: MIT License
Classifier: Framework :: Flask
Classifier: Programming Language :: Python :: 3
Classifier: License :: OSI Approved :: MIT License
Classifier: Operating System :: OS Independent
Requires-Python: >=3.9
License-File: LICENSE
Requires-Dist: flask>=2.2
Requires-Dist: httpx==0.28.1
Requires-Dist: MarkupSafe==3.0.3
Requires-Dist: minify_html==0.18.1
Dynamic: license-file
